agentmakestudio/README.md
agentmakestudio/main.py
agentmakestudio/requirements.txt
agentmakestudio/version.txt
agentmakestudio-0.0.10.dist-info/LICENSE
agentmakestudio-0.0.10.dist-info/METADATA
agentmakestudio-0.0.10.dist-info/WHEEL
agentmakestudio-0.0.10.dist-info/entry_points.txt
agentmakestudio-0.0.10.dist-info/top_level.txt
agentmakestudio-0.0.10.dist-info/RECORD
